fermium/__init__.py
fermium/fermium.py
fermium/fermium_cli.py
fermium-0.1.0.dist-info/AUTHORS.md
fermium-0.1.0.dist-info/LICENSE
fermium-0.1.0.dist-info/METADATA
fermium-0.1.0.dist-info/WHEEL
fermium-0.1.0.dist-info/entry_points.txt
fermium-0.1.0.dist-info/top_level.txt
fermium-0.1.0.dist-info/RECORD
