Metadata-Version: 2.1
Name: fermium
Version: 0.1.0
Summary: placeholder
Home-page: https://github.com/Stephen-RA-King/fermium
Download-URL: 
Author: Stephen R A King
Author-email: stephen.ra.king@gmail.com
Maintainer: Stephen R A King
Maintainer-email: stephen.ra.king@gmail.com
License: MIT
Keywords: utility
Platform: Any
Classifier: Development Status :: 1 - Planning
Classifier: Environment :: Console
Classifier: Intended Audience :: Developers
Classifier: Natural Language :: English
Classifier: Programming Language :: Python :: 3
Classifier: Programming Language :: Python :: 3 :: Only
Classifier: Programming Language :: Python :: 3.8
Classifier: Programming Language :: Python :: 3.9
Classifier: Programming Language :: Python :: 3.10
Requires-Python: >=3.8
License-File: LICENSE
License-File: AUTHORS.md
